{
  "active": false,
  "mode": "ultrawork",
  "current_phase": "complete",
  "started_at": "2026-04-15T03:27:53.317Z",
  "updated_at": "2026-04-15T03:27:53.317Z",
  "session_id": "omx-1776222702773-8t7u4d",
  "thread_id": "019d8f1f-a3d6-7813-add8-e228ca480791",
  "turn_id": "019d8f28-4db5-78b3-a169-4af3f42aa8fd",
  "iteration": 4,
  "task_description": "Completed harness-defined split of observation-storage.ts into evidence store, repository, and feed modules with compatibility facades and green verification.",
  "completed_at": "2026-04-14T20:27:00-07:00"
}